{
    "music": 12,
    "stage": 12,
    "player": {
        "character": "sakuya",
        "palette": 0,
        "deck": [],
        "pos": 400
    },
    "dummy": {
        "character": "meirin",
        "palette": 0,
        "deck": [],
        "pos": {
            "x": 800,
            "y": 0
        }
    },
    "type": "combo",

    "expected": "66c hj9:40 j5a:15 j2a 66a:40 d623b",
    "skills": [
        [0, 0],
        [0, 0],
        [0, 0],
        [0, 0]
    ],
    "weather": 16,
    "disable_limit": false,
    "uniform_card_cost": 5,
    "hand": [],
    "play_combo_after_intro": true,
    "hint": [

    ],
    "score": [
    {
        "min_hits": 6,
        "min_damage": 2500,
        "min_limit": 85,
        "max_limit": 130
    },
    {   
        "min_hits": 8,
        "min_damage" : 2585
    },
    {
        "max_attempts": 10
    },
    {
        "max_attempts": 5
    }
    ]
}