{
    "name": "Basic combos",
    "category": "Remilia Scarlet",
    "characters": [
        "remilia",
        "reimu"
    ],
    "stand": {
        "isPath": false,
        "path": "data/stand/remilia.bmp"
    },
    "description": "Lorem ipsum dolor sit<br>amet, consectetur adipiscing elit,<br>sed do eiusmod tempor incididunt ut<br>labore et dolore magna aliqua.<br>Ut enim ad minim veniam, quis<br>nostrud exercitation ullamco laboris<br>nisi ut aliquip ex ea commodo consequat.<br>",
    "author": "PinkySmile",
    "icon": {
        "isPath": false,
        "path": "data/character/remilia/face/face000.bmp",
        "offset": {
            "x": 1,
            "y": 0
        },
        "scale": 0.60,
        "xMirror": true,
        "yMirror": false
    },
    "scenarios": [
        {
            "name": "BnB midscreen 1",
            "face": "remilia",
            "file": "bnbmid1.json",
            "preview": "bnbmid1.png",
            "description": "Lorem ipsum dolor sit<br>amet, consectetur adipiscing elit,<br>sed do eiusmod tempor incididunt ut<br>labore et dolore magna aliqua.<br>Ut enim ad minim veniam, quis<br>nostrud exercitation ullamco laboris<br>nisi ut aliquip ex ea commodo consequat.<br>"
        },
        {
            "name": "BnB midscreen 2",
            "face": "remilia",
            "file": "bnbmid2.json",
            "preview": "bnbmid2.png",
            "description": ""
        },
        {
            "name": "BnB midscreen 3",
            "face": "remilia",
            "file": "bnbmid3.json",
            "preview": "bnbmid3.png",
            "description": ""
        },
        {
            "name": "BnB corner 1",
            "face": "remilia",
            "file": "bnbcorn1.json",
            "preview": "bnbcorn1.png",
            "description": ""
        },
        {
            "name": "BnB corner 2",
            "face": "remilia",
            "file": "bnbcorn2.json",
            "preview": "bnbcorn2.png",
            "description": ""
        },
        {
            "name": "BnB corner 3",
            "face": "remilia",
            "file": "bnbcorn3.json",
            "preview": "bnbcorn3.png",
            "description": ""
        },
        {
            "name": "BnB aerial 1",
            "face": "remilia",
            "file": "bnbair1.json",
            "preview": "bnbair1.png",
            "description": ""
        },
        {
            "name": "BnB aerial 2",
            "face": "remilia",
            "file": "bnbair2.json",
            "preview": "bnbair2.png",
            "description": ""
        },
        {
            "name": "BnB aerial 3",
            "face": "remilia",
            "file": "bnbair3.json",
            "description": ""
        }
    ]
}